todoai_cli/__init__.py
todoai_cli/cli.py
todoai_cli/config_store.py
todoai_cli/deploy.py
todoai_cli/edge_client.py
todoai_cli/project_selectors.py
todoai_cli-0.1.5.dist-info/licenses/LICENSE
todoai_cli-0.1.5.dist-info/METADATA
todoai_cli-0.1.5.dist-info/WHEEL
todoai_cli-0.1.5.dist-info/entry_points.txt
todoai_cli-0.1.5.dist-info/top_level.txt
todoai_cli-0.1.5.dist-info/RECORD
